pagination_sorting/__init__.py
pagination_sorting/pagination.py
pagination_sorting/sorting.py
tests/__init__.py
tests/test_pagination.py
tests/test_sorting.py
pagination_sorting-0.1.1.dist-info/LICENSE
pagination_sorting-0.1.1.dist-info/METADATA
pagination_sorting-0.1.1.dist-info/WHEEL
pagination_sorting-0.1.1.dist-info/top_level.txt
pagination_sorting-0.1.1.dist-info/RECORD
